Metadata-Version: 2.1
Name: Mensajes-chrishiguera97
Version: 6.0
Summary: Un paquete para saludar y despedir
Home-page: https://www.christian.dev
Author: Christian Higuera Gómez
Author-email: christianhiguera2007@hotmail.com
Classifier: Environment :: Console
Classifier: Intended Audience :: Developers
Classifier: License :: OSI Approved :: MIT License
Classifier: Operating System :: OS Independent
Classifier: Programming Language :: Python
Classifier: Programming Language :: Python :: 3.9
Classifier: Programming Language :: Python :: 3.10
Classifier: Topic :: Utilities
License-File: LICENSE
Requires-Dist: numpy>=2.1.3
